docker/www/prestart.sh
gitbrag/__init__.py
gitbrag/_version.py
gitbrag/cli.py
gitbrag/py.typed
gitbrag/settings.py
gitbrag/www.py
gitbrag/conf/__init__.py
gitbrag/conf/cache.py
gitbrag/conf/github.py
gitbrag/conf/settings.py
gitbrag/services/auth.py
gitbrag/services/background_tasks.py
gitbrag/services/cache.py
gitbrag/services/encryption.py
gitbrag/services/formatter.py
gitbrag/services/jinja.py
gitbrag/services/language_analyzer.py
gitbrag/services/pr_size.py
gitbrag/services/reports.py
gitbrag/services/session.py
gitbrag/services/task_tracking.py
gitbrag/services/github/__init__.py
gitbrag/services/github/auth.py
gitbrag/services/github/client.py
gitbrag/services/github/models.py
gitbrag/services/github/oauth.py
gitbrag/services/github/pullrequests.py
gitbrag/services/github/stargazers.py
gitbrag/services/github/web_oauth.py
gitbrag/static/.gitkeep
gitbrag/static/css/styles.css
gitbrag/static/images/og-image.png
gitbrag/static/js/report_refresh.js
gitbrag/static/js/theme.js
gitbrag/templates/.gitkeep
gitbrag/templates/base.html
gitbrag/templates/error.html
gitbrag/templates/home.html
gitbrag/templates/user_report.html
gitbrag/templates/components/pr_table.html
gitbrag/templates/components/repo_section.html
gitbrag/templates/components/summary_card.html
gitbrag-1.1.2.dist-info/licenses/LICENSE
openspec/AGENTS.md
openspec/project.md
openspec/changes/archive/2025-12-14-add-github-contribution-collection/design.md
openspec/changes/archive/2025-12-14-add-github-contribution-collection/proposal.md
openspec/changes/archive/2025-12-14-add-github-contribution-collection/tasks.md
openspec/changes/archive/2025-12-14-add-github-contribution-collection/specs/contribution-report-cli/spec.md
openspec/changes/archive/2025-12-14-add-github-contribution-collection/specs/github-authentication/spec.md
openspec/changes/archive/2025-12-14-add-github-contribution-collection/specs/github-pull-request-collection/spec.md
openspec/changes/archive/2025-12-27-add-star-increase-column/design.md
gitbrag-1.1.2.dist-info/METADATA
gitbrag-1.1.2.dist-info/WHEEL
gitbrag-1.1.2.dist-info/entry_points.txt
gitbrag-1.1.2.dist-info/top_level.txt
gitbrag-1.1.2.dist-info/RECORD
