Metadata-Version: 2.4
Name: gitbrag
Version: 1.1.2
Summary: Create a brag list of open source contributions
Author: Robert Hafner
License: MIT License
Requires-Python: >=3.10
License-File: LICENSE
Requires-Dist: aiocache
Requires-Dist: cryptography
Requires-Dist: fastapi
Requires-Dist: httpx
Requires-Dist: itsdangerous
Requires-Dist: jinja2
Requires-Dist: pydantic~=2.0
Requires-Dist: pydantic-settings
Requires-Dist: redis
Requires-Dist: rich
Requires-Dist: typer
Requires-Dist: uvicorn[standard]
Dynamic: license-file
